{
  "albumData": {
    "title": "130807 3D printed ping pong net post",
    "date": "Aug 7, 2013 8:05:28 PM",
    "access": "public",
    "description": "",
    "location": "",
    "geoInfo": null
  },
  "media": [
    {
      "tags": [],
      "description": "",
      "title": "IMG_3902.jpg",
      "people": [],
      "comments": [],
      "url": "https://lh3.googleusercontent.com/-E2M5_0VfUmY/Ulv0y0zm38I/AAAAAAAAY5Q/gWQMrp8TcNkKAmGdE9myKJir6fIzbuTXg/s0-d/IMG_3902.jpg",
      "geoInfo": null,
      "geoInfoExif": null,
      "imageViews": 239,
      "license": null
    },
    {
      "tags": [],
      "description": "",
      "title": "IMG_3903.jpg",
      "people": [],
      "comments": [],
      "url": "https://lh3.googleusercontent.com/-nXTAbRWcvKg/Ulv0zjkZQiI/AAAAAAAAY5c/KxTnL_wP7DIFOudjMa4-9_Z5xkgzLKY1w/s0-d/IMG_3903.jpg",
      "geoInfo": null,
      "geoInfoExif": null,
      "imageViews": 0,
      "license": null
    },
    {
      "tags": [],
      "description": "",
      "title": "IMG_3904.jpg",
      "people": [],
      "comments": [],
      "url": "https://lh3.googleusercontent.com/-zKB0lb_emqs/Ulv00Fhl9_I/AAAAAAAAY50/6oxtbHSWhXocRKlkDmXcau8VfzWbvL_Qw/s0-d/IMG_3904.jpg",
      "geoInfo": null,
      "geoInfoExif": null,
      "imageViews": 0,
      "license": null
    },
    {
      "tags": [],
      "description": "",
      "title": "IMG_3905.jpg",
      "people": [],
      "comments": [],
      "url": "https://lh3.googleusercontent.com/-K45JWUwdoDI/Ulv00wKT78I/AAAAAAAAY5w/IKCfOZeSX0sySvy3kh7GXHthYjFA8fSSw/s0-d/IMG_3905.jpg",
      "geoInfo": null,
      "geoInfoExif": null,
      "imageViews": 0,
      "license": null
    }
  ]
}