{
  "albumData": {
    "title": "November 21, 2015",
    "date": "Nov 21, 2015 5:08:16 AM",
    "access": "protected",
    "description": "",
    "location": "",
    "geoInfo": null
  },
  "media": [
    {
      "tags": [],
      "description": "",
      "title": "20151121_093619.jpg",
      "people": [],
      "comments": [],
      "url": "https://lh3.googleusercontent.com/-SahTD5ndFDI/VlBswlP_rCI/AAAAAAAAvaQ/MMiSuyu1TjMDsUdEONwUwQhLQIoGumRtg/s0-d/20151121_093619.jpg",
      "geoInfo": null,
      "geoInfoExif": null,
      "imageViews": 0,
      "license": null
    },
    {
      "tags": [],
      "description": "",
      "title": "20151121_093623.jpg",
      "people": [],
      "comments": [],
      "url": "https://lh3.googleusercontent.com/-xQKgSR6ja0w/VlBsxEYoQmI/AAAAAAAAvZw/ibCrpxIvxxAlMivkTa_YULHJc7dVK5Tig/s0-d/20151121_093623.jpg",
      "geoInfo": null,
      "geoInfoExif": null,
      "imageViews": 0,
      "license": null
    },
    {
      "tags": [],
      "description": "",
      "title": "20151121_093627.jpg",
      "people": [],
      "comments": [],
      "url": "https://lh3.googleusercontent.com/-MCOd8JnnNGc/VlBsxHkdEbI/AAAAAAAAvZ4/d7G12vqc3i4_n5Drx6PzJoQ6rt9SHnCvw/s0-d/20151121_093627.jpg",
      "geoInfo": null,
      "geoInfoExif": null,
      "imageViews": 0,
      "license": null
    },
    {
      "tags": [],
      "description": "",
      "title": "20151121_093849.jpg",
      "people": [],
      "comments": [],
      "url": "https://lh3.googleusercontent.com/-vRTVehGArRU/VlBsxhShOUI/AAAAAAAAvaE/F7xurWI2UHcXY8TW_SUqrfN9gufKLreew/s0-d/20151121_093849.jpg",
      "geoInfo": null,
      "geoInfoExif": null,
      "imageViews": 0,
      "license": null
    },
    {
      "tags": [],
      "description": "",
      "title": "20151121_103750.jpg",
      "people": [],
      "comments": [],
      "url": "https://lh3.googleusercontent.com/-JnNAPyWaaQg/VlBsyma5yaI/AAAAAAAAvaM/qmM94DxaOnsFXK_hQDtv2u29WCulKfRvA/s0-d/20151121_103750.jpg",
      "geoInfo": null,
      "geoInfoExif": null,
      "imageViews": 0,
      "license": null
    },
    {
      "tags": [],
      "description": "",
      "title": "20151121_104012.jpg",
      "people": [],
      "comments": [],
      "url": "https://lh3.googleusercontent.com/-WLGPwaw_COY/VlBsyRrcrxI/AAAAAAAAvaI/GBX2qlF9Uzw302zn_lCWwktrnRtis3kow/s0-d/20151121_104012.jpg",
      "geoInfo": null,
      "geoInfoExif": null,
      "imageViews": 0,
      "license": null
    },
    {
      "tags": [],
      "description": "",
      "title": "20151121_104054.mp4",
      "people": [],
      "comments": [],
      "url": "https://video.googleusercontent.com/JT8t4mU1cRCrwFleOHNj-wZQs2RwGU1FOWpNhehbfPpc9aFrOA_CkWi6YN2uFoSueN7v6iSOwX2cYb0GpA",
      "geoInfo": null,
      "geoInfoExif": null,
      "imageViews": 0,
      "license": null
    },
    {
      "tags": [],
      "description": "",
      "title": "20151121_105011.jpg",
      "people": [],
      "comments": [],
      "url": "https://lh3.googleusercontent.com/-x0Sh51TMFGw/VlBs43GMDfI/AAAAAAAAvag/8AKVSViVUyYh2yoNCIU2r3WGIPtaPc37Q/s0-d/20151121_105011.jpg",
      "geoInfo": null,
      "geoInfoExif": null,
      "imageViews": 0,
      "license": null
    },
    {
      "tags": [],
      "description": "",
      "title": "20151121_105016.jpg",
      "people": [],
      "comments": [],
      "url": "https://lh3.googleusercontent.com/-hfQyxhnVDYQ/VlBs5Yl_qhI/AAAAAAAAvao/aOgEEoy_4kQh4Bu6QhcwASAKcWad51qSA/s0-d/20151121_105016.jpg",
      "geoInfo": null,
      "geoInfoExif": null,
      "imageViews": 0,
      "license": null
    },
    {
      "tags": [],
      "description": "",
      "title": "20151121_105025.jpg",
      "people": [],
      "comments": [],
      "url": "https://lh3.googleusercontent.com/-tHN3VyKDZPc/VlBs52ujP8I/AAAAAAAAvbA/wRktDf6ynhkgK_DrY_bJ0R8SRKiEMIESg/s0-d/20151121_105025.jpg",
      "geoInfo": null,
      "geoInfoExif": null,
      "imageViews": 0,
      "license": null
    },
    {
      "tags": [],
      "description": "",
      "title": "20151121_105043.jpg",
      "people": [],
      "comments": [],
      "url": "https://lh3.googleusercontent.com/-1-YJmwxGnPA/VlBs6qijf9I/AAAAAAAAvaw/_oI-ETSyRFIEhQNNnpTAk97XmK3-KhxMg/s0-d/20151121_105043.jpg",
      "geoInfo": null,
      "geoInfoExif": null,
      "imageViews": 0,
      "license": null
    },
    {
      "tags": [],
      "description": "",
      "title": "20151121_105045.jpg",
      "people": [],
      "comments": [],
      "url": "https://lh3.googleusercontent.com/-0gOLHgabA20/VlBs7UEzQhI/AAAAAAAAvbE/rrWSM0WQSsMW9Tcqx7S04FUA4N2qpy5Ag/s0-d/20151121_105045.jpg",
      "geoInfo": null,
      "geoInfoExif": null,
      "imageViews": 0,
      "license": null
    },
    {
      "tags": [],
      "description": "",
      "title": "20151121_105048.jpg",
      "people": [],
      "comments": [],
      "url": "https://lh3.googleusercontent.com/-OFnpwgvLlsA/VlBs8CQU5pI/AAAAAAAAvbM/1UkJpGVzhbAjUPTsqPIk2NFRIDfXtiWQw/s0-d/20151121_105048.jpg",
      "geoInfo": null,
      "geoInfoExif": null,
      "imageViews": 0,
      "license": null
    },
    {
      "tags": [],
      "description": "",
      "title": "20151121_114942.jpg",
      "people": [],
      "comments": [],
      "url": "https://lh3.googleusercontent.com/-dnCQn3TwKsY/VlBs8wUIqJI/AAAAAAAAvbY/dsoj_pXqj_cCufBcVb0043z6HnnOzURhA/s0-d/20151121_114942.jpg",
      "geoInfo": null,
      "geoInfoExif": null,
      "imageViews": 0,
      "license": null
    },
    {
      "tags": [],
      "description": "",
      "title": "20151121_114950.jpg",
      "people": [],
      "comments": [],
      "url": "https://lh3.googleusercontent.com/-0-0iChk1V4E/VlBs9RXJYTI/AAAAAAAAvbc/K69dxUjMaTcZ4woGvEj5qH1Pv6EwfJWGg/s0-d/20151121_114950.jpg",
      "geoInfo": null,
      "geoInfoExif": null,
      "imageViews": 0,
      "license": null
    },
    {
      "tags": [],
      "description": "",
      "title": "20151121_120845.jpg",
      "people": [],
      "comments": [],
      "url": "https://lh3.googleusercontent.com/-6S0MqxsSc4s/VlBs-LajIHI/AAAAAAAAvbk/wOCiTirf4l4ci2syVwzTbB36MwuVi66nQ/s0-d/20151121_120845.jpg",
      "geoInfo": null,
      "geoInfoExif": null,
      "imageViews": 0,
      "license": null
    },
    {
      "tags": [],
      "description": "",
      "title": "20151121_120905_HDR.jpg",
      "people": [],
      "comments": [],
      "url": "https://lh3.googleusercontent.com/-JrJhQ1CVhbQ/VlBs_OQpUzI/AAAAAAAAvbs/AoquOMbYI6oGBQuB_XaKUyN8r9wUcl9HA/s0-d/20151121_120905_HDR.jpg",
      "geoInfo": null,
      "geoInfoExif": null,
      "imageViews": 0,
      "license": null
    },
    {
      "tags": [],
      "description": "",
      "title": "20151121_120941.jpg",
      "people": [],
      "comments": [],
      "url": "https://lh3.googleusercontent.com/-gfrX5VUg0qY/VlBs_g7XstI/AAAAAAAAvbw/J6y_YhRYBoM-WKuS0JjZgskUFHd11ECSw/s0-d/20151121_120941.jpg",
      "geoInfo": null,
      "geoInfoExif": null,
      "imageViews": 0,
      "license": null
    },
    {
      "tags": [],
      "description": "",
      "title": "20151121_120943.jpg",
      "people": [],
      "comments": [],
      "url": "https://lh3.googleusercontent.com/-i6bSy2E8Fpo/VlBtATFU6PI/AAAAAAAAvdg/2CHeIb2L5kk6XJJ31HLNPjX5VVcJNSDiA/s0-d/20151121_120943.jpg",
      "geoInfo": null,
      "geoInfoExif": null,
      "imageViews": 0,
      "license": null
    },
    {
      "tags": [],
      "description": "",
      "title": "20151121_120959.jpg",
      "people": [],
      "comments": [],
      "url": "https://lh3.googleusercontent.com/-AN9URHl1k6w/VlBtBKgur0I/AAAAAAAAvcA/E0JP5hY_4osNmG8YvXlL131yzDBllvUFQ/s0-d/20151121_120959.jpg",
      "geoInfo": null,
      "geoInfoExif": null,
      "imageViews": 0,
      "license": null
    },
    {
      "tags": [],
      "description": "",
      "title": "20151121_121000.jpg",
      "people": [],
      "comments": [],
      "url": "https://lh3.googleusercontent.com/-1wrEhZh3y8s/VlBtCENu94I/AAAAAAAAvcM/1iVOLwIB0r8llBddND43snpzW_VlDAExQ/s0-d/20151121_121000.jpg",
      "geoInfo": null,
      "geoInfoExif": null,
      "imageViews": 0,
      "license": null
    },
    {
      "tags": [],
      "description": "",
      "title": "20151121_121002.jpg",
      "people": [],
      "comments": [],
      "url": "https://lh3.googleusercontent.com/-SOT-nYoNp8g/VlBtDK7BtCI/AAAAAAAAvcU/12GNaALVwBQNjPDmVofL5MKgV1TR3x5-g/s0-d/20151121_121002.jpg",
      "geoInfo": null,
      "geoInfoExif": null,
      "imageViews": 0,
      "license": null
    },
    {
      "tags": [],
      "description": "",
      "title": "20151121_121003.jpg",
      "people": [],
      "comments": [],
      "url": "https://lh3.googleusercontent.com/-iR9H2FJy9TI/VlBtD0dfA4I/AAAAAAAAvcY/mZfD8eMzVEw7rLXjw4Rl8-BgpuxzyZPdA/s0-d/20151121_121003.jpg",
      "geoInfo": null,
      "geoInfoExif": null,
      "imageViews": 0,
      "license": null
    },
    {
      "tags": [],
      "description": "",
      "title": "20151121_093619.jpg",
      "people": [],
      "comments": [],
      "url": "https://lh3.googleusercontent.com/-Fpy-I1B_gvk/VlBtE4ARsRI/AAAAAAAAvco/4xSdIDLir4spziqMnqtNRgn9aHDzVIeew/s0-d/20151121_093619.jpg",
      "geoInfo": null,
      "geoInfoExif": null,
      "imageViews": 0,
      "license": null
    }
  ]
}